wslexplorer/__init__.py
wslexplorer/config.py
wslexplorer/win_explorer.py
wslexplorer-0.1.2.dist-info/DESCRIPTION.rst
wslexplorer-0.1.2.dist-info/METADATA
wslexplorer-0.1.2.dist-info/RECORD
wslexplorer-0.1.2.dist-info/WHEEL
wslexplorer-0.1.2.dist-info/entry_points.txt
wslexplorer-0.1.2.dist-info/metadata.json
wslexplorer-0.1.2.dist-info/top_level.txt
