Metadata-Version: 2.0
Name: wslexplorer
Version: 0.1.2
Summary: Simple script that launches Window Explorer from Windows Subsystem for Linux
Home-page: https://github.com/scottfp/wslexplorer
Author: Scott Pritchard
Author-email: scottfp@gmail.com
License: MIT
Platform: UNKNOWN
Requires-Dist: Click
Requires-Dist: ruamel.yaml
